failstodeliver
