Metadata-Version: 1.2
Name: failstodeliver
Version: 0.0.2
Summary: A simple package to download failstodeliver data from SEC EDGAR Databse
Home-page: https://github.com/Yuvrajchandra/failstodeliver
Author: Yuvraj Chandra
Author-email: Singhyuvraj179@gmail.com
License: MIT
Download-URL: https://github.com/Yuvrajchandra/failstodeliver/archive/v0.0.2.tar.gz
Keywords: EDGAR,SEC,failstodeliver,Database
Platform: UNKNOWN
Classifier: Programming Language :: Python :: 3
Classifier: License :: OSI Approved :: MIT License
Classifier: Operating System :: OS Independent
Requires-Python: >=3.6
